{
    "Triathlon": 10,
    "Artistic Swimming": 10,
    "Weightlifting": 10,
    "Canoe Slalom": 10,
    "Artistic Gymnastics": 10,
    "Surfing": 10,
    "Road cycling": 10,
    "Shooting": 10,
    "Canoe Sprint": 10,
    "American Football": 10,
    "Sport Climbing": 10,
    "Golf": 10,
    "BMX Racing": 10,
    "Track Cycling": 10,
    "Mountain biking": 10,
    "Basketball": 10,
    "Volleyball": 10,
    "Baseball": 10,
    "Football": 10,
    "Athletics": 9,
    "Judo": 9,
    "Swimming": 9,
    "Rowing": 9,
    "Diving": 9,
    "Equestrian": 9,
    "Rhythmic Gymnastics": 9,
    "Marathon Swimming": 9,
    "Table Tennis": 9,
    "Badminton": 9,
    "Ice Hockey": 9,
    "Fencing": 9,
    "Rugby Sevens": 9,
    "Handball": 9,
    "Skateboarding": 9,
    "Tennis": 9,
    "Freestyle BMX": 9,
    "Beach Volleyball": 9,
    "Esports": 10,
    "Rugby Union": 9,
    "Boxing": 8,
    "Sailing": 8,
    "Modern Pentathlon": 8,
    "Archery": 8,
    "Breaking": 8,
    "Trampolining": 8,
    "Water Polo": 8,
    "Flag football": 9,
    "Taekwondo": 7,
    "3x3 Basketball": 7,
    "Wrestling": 6,
    "Ultimate Frisbee": 10,
    "Cricket": 8
}